.gitignore
CHANGES.txt
MANIFEST.in
README.txt
bootstrap.py
buildout.cfg
development.ini
setup.cfg
setup.py
docs/.gitignore
docs/Makefile
docs/conf.py
docs/index.txt
pyramid_formalchemy/__init__.py
pyramid_formalchemy/actions.py
pyramid_formalchemy/events.py
pyramid_formalchemy/i18n.py
pyramid_formalchemy/paster.py
pyramid_formalchemy/resources.py
pyramid_formalchemy/utils.py
pyramid_formalchemy/views.py
pyramid_formalchemy.egg-info/PKG-INFO
pyramid_formalchemy.egg-info/SOURCES.txt
pyramid_formalchemy.egg-info/dependency_links.txt
pyramid_formalchemy.egg-info/entry_points.txt
pyramid_formalchemy.egg-info/not-zip-safe
pyramid_formalchemy.egg-info/requires.txt
pyramid_formalchemy.egg-info/top_level.txt
pyramid_formalchemy/locale/pyramid_formalchemy.pot
pyramid_formalchemy/locale/de/LC_MESSAGES/pyramid_formalchemy.mo
pyramid_formalchemy/locale/de/LC_MESSAGES/pyramid_formalchemy.po
pyramid_formalchemy/locale/fr/LC_MESSAGES/pyramid_formalchemy.mo
pyramid_formalchemy/locale/fr/LC_MESSAGES/pyramid_formalchemy.po
pyramid_formalchemy/locale/pt_BR/LC_MESSAGES/pyramid_formalchemy.mo
pyramid_formalchemy/locale/pt_BR/LC_MESSAGES/pyramid_formalchemy.po
pyramid_formalchemy/paster_templates/pyramid_fa/README_FORMALCHEMY.txt
pyramid_formalchemy/paster_templates/pyramid_fa/+package+/faforms.py_tmpl
pyramid_formalchemy/paster_templates/pyramid_fa/+package+/fainit.py_tmpl
pyramid_formalchemy/paster_templates/pyramid_fa/+package+/faroutes.py_tmpl
pyramid_formalchemy/static/add.png
pyramid_formalchemy/static/admin.css
pyramid_formalchemy/static/delete.png
pyramid_formalchemy/static/edit.png
pyramid_formalchemy/templates/admin/edit.pt
pyramid_formalchemy/templates/admin/edit.pt.py
pyramid_formalchemy/templates/admin/listing.pt
pyramid_formalchemy/templates/admin/listing.pt.py
pyramid_formalchemy/templates/admin/master.pt
pyramid_formalchemy/templates/admin/master.pt.py
pyramid_formalchemy/templates/admin/models.pt
pyramid_formalchemy/templates/admin/models.pt.py
pyramid_formalchemy/templates/admin/new.pt
pyramid_formalchemy/templates/admin/new.pt.py
pyramid_formalchemy/templates/admin/show.pt
pyramid_formalchemy/templates/admin/show.pt.py
pyramid_formalchemy/templates/forms/fieldset.pt
pyramid_formalchemy/templates/forms/fieldset.pt.py
