Metadata-Version: 1.0
Name: pyramid_formalchemy
Version: 0.4.3
Summary: FormAlchemy plugins and helpers for Pyramid
Home-page: http://docs.formalchemy.org/pyramid_formalchemy/
Author: Gael Pasgrimaud
Author-email: gael@gawel.org
License: UNKNOWN
Keywords: web pyramid pylons formalchemy
Platform: UNKNOWN
Classifier: Programming Language :: Python
Classifier: Framework :: Pylons
Classifier: Topic :: Internet :: WWW/HTTP
Classifier: Topic :: Internet :: WWW/HTTP :: WSGI :: Application
